MANIFEST.in
README.md
setup.py
psrmodels.egg-info/PKG-INFO
psrmodels.egg-info/SOURCES.txt
psrmodels.egg-info/dependency_links.txt
psrmodels.egg-info/requires.txt
psrmodels.egg-info/top_level.txt
psrmodels/c/libbivarmargins.c
psrmodels/c/libbivarmargins.h
psrmodels/c/libtimedependence.c
psrmodels/c/libtimedependence.h
psrmodels/c/libunivarmargins.c
psrmodels/c/libunivarmargins.h
psrmodels/c/mtwist-1.5/mtwist.c
psrmodels/c/mtwist-1.5/mtwist.h
psrmodels/c/mtwist-1.5/randistrs.h
psrmodels/c_builders/build_bivarmargins.py
psrmodels/c_builders/build_timedependence.py
psrmodels/c_builders/build_univarmargins.py
psrmodels/time_collapsed/BivariateConvGenDist.py
psrmodels/time_collapsed/BivariateHindcastMargin.py
psrmodels/time_collapsed/BivariateHindcastNetDemand.py
psrmodels/time_collapsed/BivariateLogisticNetDemand.py
psrmodels/time_collapsed/BivariateSystemSimulator.py
psrmodels/time_collapsed/ConvGenDistribution.py
psrmodels/time_collapsed/EnergyUnservedExplorer.py
psrmodels/time_collapsed/MonteCarloEstimator.py
psrmodels/time_collapsed/UnivariateBayesianEVMargin.py
psrmodels/time_collapsed/UnivariateEVMargin.py
psrmodels/time_collapsed/UnivariateHindcastMargin.py
psrmodels/time_collapsed/__init__.py
psrmodels/time_dependent/BivariateHindcastMargin.py
psrmodels/time_dependent/ConvGenDistribution.py
psrmodels/time_dependent/__init__.py
test/test_library.py