Metadata-Version: 2.1
Name: psrmodels
Version: 1.2.7
Summary: Models for security of supply in power systems' reliability
Home-page: https://bitbucket.com/nestorsag/phd
Author: Nestor Sanchez
Author-email: nestor.sag@gmail.com
License: MIT
Download-URL: https://github.com/nestorSag/psrmodels/archive/1.2.7.tar.gz
Platform: UNKNOWN
Classifier: Programming Language :: Python :: 3
Classifier: License :: OSI Approved :: MIT License
Classifier: Operating System :: OS Independent
